projeto1_portas_logicas/mux8way16/mux8way16.v
module mux8way16(
    input [15:0] a,
    input [15:0] b,
    input [15:0] c,
    input [15:0] d,
    input [15:0] e,
    input [15:0] f,
    input [15:0] g,
    input [15:0] h,
    input [2:0] sel,
    output [15:0] out
);
    reg [15:0] temp_out;

    always @(*) begin
        case (sel)
            3'b000: temp_out = a;
            3'b001: temp_out = b;
            3'b010: temp_out = c;
            3'b011: temp_out = d;
            3'b100: temp_out = e;
            3'b101: temp_out = f;
            3'b110: temp_out = g;
            3'b111: temp_out = h;
            default: temp_out = 16'bx;
        endcase
    end
    
    assign out = temp_out;
endmodule

projeto1_portas_logicas/mux8way16/tb_mux8way16.v
`timescale 1ns / 1ps

module tb_mux8way16;
    reg [15:0] input_a;
    reg [15:0] input_b;
    reg [15:0] input_c;
    reg [15:0] input_d;
    reg [15:0] input_e;
    reg [15:0] input_f;
    reg [15:0] input_g;
    reg [15:0] input_h;
    reg [2:0] input_sel;
    wire [15:0] output_out;

    mux8way16 dut (
        .a(input_a),
        .b(input_b),
        .c(input_c),
        .d(input_d),
        .e(input_e),
        .f(input_f),
        .g(input_g),
        .h(input_h),
        .sel(input_sel),
        .out(output_out)
    );

    initial begin
        $dumpfile("mux8way16.vcd");
        $dumpvars(0, tb_mux8way16);

        $display("Time | In0 (hex) | In1 (hex) | In2 (hex) | In3 (hex) | In4 (hex) | In5 (hex) | In6 (hex) | In7 (hex) | SEL (bin) | Out (hex)");
        $monitor("%0t | %h | %h | %h | %h | %h | %h | %h | %h | %b | %h",
                 $time, input_a, input_b, input_c, input_d, input_e, input_f, input_g, input_h, input_sel, output_out);

        input_a = 16'h0000; input_b = 16'h1111; input_c = 16'h2222; input_d = 16'h3333;
        input_e = 16'h4444; input_f = 16'h5555; input_g = 16'h6666; input_h = 16'h7777;
        input_sel = 3'b000;
        #0.1;

        input_sel = 3'b000; #5;
        input_sel = 3'b001; #5;
        input_sel = 3'b010; #5;
        input_sel = 3'b011; #5;
        input_sel = 3'b100; #5;
        input_sel = 3'b101; #5;
        input_sel = 3'b110; #5;
        input_sel = 3'b111; #5;

        input_a = 16'hAAAA; input_b = 16'hBBBB; input_c = 16'hCCCC; input_d = 16'hDDDD;
        input_e = 16'hEEEE; input_f = 16'hFFFF; input_g = 16'h0123; input_h = 16'h4567;
        #10;

        input_sel = 3'b000; #5;
        input_sel = 3'b001; #5;
        input_sel = 3'b010; #5;
        input_sel = 3'b011; #5;
        input_sel = 3'b100; #5;
        input_sel = 3'b101; #5;
        input_sel = 3'b110; #5;
        input_sel = 3'b111; #5;

        $finish;
    end

endmodule

projeto1_portas_logicas/mux8way16/mux8way16.vcd
$date
	Sat Jul  5 14:05:40 2025
$end
$version
	Icarus Verilog
$end
$timescale
	1ps
$end
$scope module tb_mux8way16 $end
$var wire 16 ! output_out [15:0] $end
$var reg 16 " input_a [15:0] $end
$var reg 16 # input_b [15:0] $end
$var reg 16 $ input_c [15:0] $end
$var reg 16 % input_d [15:0] $end
$var reg 16 & input_e [15:0] $end
$var reg 16 ' input_f [15:0] $end
$var reg 16 ( input_g [15:0] $end
$var reg 16 ) input_h [15:0] $end
$var reg 3 * input_sel [2:0] $end
$scope module dut $end
$var wire 16 + a [15:0] $end
$var wire 16 , b [15:0] $end
$var wire 16 - c [15:0] $end
$var wire 16 . d [15:0] $end
$var wire 16 / e [15:0] $end
$var wire 16 0 f [15:0] $end
$var wire 16 1 g [15:0] $end
$var wire 16 2 h [15:0] $end
$var wire 16 3 out [15:0] $end
$var wire 3 4 sel [2:0] $end
$var reg 16 5 temp_out [15:0] $end
$upscope $end
$upscope $end
$enddefinitions $end
$comment Show the parameter values. $end
$dumpall
$end
#0
$dumpvars
b0 5
b0 4
b0 3
b111011101110111 2
b110011001100110 1
b101010101010101 0
b100010001000100 /
b11001100110011 .
b10001000100010 -
b1000100010001 ,
b0 +
b0 *
b111011101110111 )
b110011001100110 (
b101010101010101 '
b100010001000100 &
b11001100110011 %
b10001000100010 $
b1000100010001 #
b0 "
b0 !
$end
#5100
b1000100010001 !
b1000100010001 3
b1000100010001 5
b1 *
b1 4
#10100
b10001000100010 !
b10001000100010 3
b10001000100010 5
b10 *
b10 4
#15100
b11001100110011 !
b11001100110011 3
b11001100110011 5
b11 *
b11 4
#20100
b100010001000100 !
b100010001000100 3
b100010001000100 5
b100 *
b100 4
#25100
b101010101010101 !
b101010101010101 3
b101010101010101 5
b101 *
b101 4
#30100
b110011001100110 !
b110011001100110 3
b110011001100110 5
b110 *
b110 4
#35100
b111011101110111 !
b111011101110111 3
b111011101110111 5
b111 *
b111 4
#40100
b100010101100111 !
b100010101100111 3
b100010101100111 5
b100010101100111 )
b100010101100111 2
b100100011 (
b100100011 1
b1111111111111111 '
b1111111111111111 0
b1110111011101110 &
b1110111011101110 /
b1101110111011101 %
b1101110111011101 .
b1100110011001100 $
b1100110011001100 -
b1011101110111011 #
b1011101110111011 ,
b1010101010101010 "
b1010101010101010 +
#50100
b1010101010101010 !
b1010101010101010 3
b1010101010101010 5
b0 *
b0 4
#55100
b1011101110111011 !
b1011101110111011 3
b1011101110111011 5
b1 *
b1 4
#60100
b1100110011001100 !
b1100110011001100 3
b1100110011001100 5
b10 *
b10 4
#65100
b1101110111011101 !
b1101110111011101 3
b1101110111011101 5
b11 *
b11 4
#70100
b1110111011101110 !
b1110111011101110 3
b1110111011101110 5
b100 *
b100 4
#75100
b1111111111111111 !
b1111111111111111 3
b1111111111111111 5
b101 *
b101 4
#80100
b100100011 !
b100100011 3
b100100011 5
b110 *
b110 4
#85100
b100010101100111 !
b100010101100111 3
b100010101100111 5
b111 *
b111 4
