project3/dff/dff.v
// dff.v
module dff (
    input wire clk,
    input wire reset,
    input wire d,
    output reg q
);

always @(posedge clk or posedge reset) begin
    if (reset)
        q <= 0;
    else
        q <= d;
end

endmodule

project3/dff/tb_dff.v
// tb_dff.v
`timescale 1ns/1ps

module tb_dff;

reg clk;
reg reset;
reg d;
wire q;

// Instancia o DFF
dff uut (
    .clk(clk),
    .reset(reset),
    .d(d),
    .q(q)
);

// Clock 10ns período
initial clk = 0;
always #5 clk = ~clk;

initial begin
    $dumpfile("dff.vcd");
    $dumpvars(0, tb_dff);

    // Inicializa sinais
    reset = 1;
    d = 0;

    // Testa reset ativo
    #10;
    reset = 0;

    // Testa entrada D
    d = 1;
    #10;
    d = 0;
    #10;
    d = 1;
    #10;

    // Testa reset novamente
    reset = 1;
    #10;
    reset = 0;

    // Testa troca rápida de D
    d = 0;
    #7;
    d = 1;
    #8;
    d = 0;
    #10;

    $finish;
end

endmodule

project3/dff/dff.vcd
$date
	Thu Jul 24 15:53:15 2025
$end
$version
	Icarus Verilog
$end
$timescale
	1ps
$end
$scope module tb_dff $end
$var wire 1 ! q $end
$var reg 1 " clk $end
$var reg 1 # d $end
$var reg 1 $ reset $end
$scope module uut $end
$var wire 1 " clk $end
$var wire 1 # d $end
$var wire 1 $ reset $end
$var reg 1 ! q $end
$upscope $end
$upscope $end
$enddefinitions $end
$comment Show the parameter values. $end
$dumpall
$end
#0
$dumpvars
1$
0#
0"
0!
$end
#5000
1"
#10000
0"
1#
0$
#15000
1!
1"
#20000
0"
0#
#25000
0!
1"
#30000
0"
1#
#35000
1!
1"
#40000
0!
0"
1$
#45000
1"
#50000
0"
0#
0$
#55000
1"
#57000
1#
#60000
0"
#65000
1"
0#
