projeto1_portas_logicas/mux16/mux16.v
module mux16(
    input [15:0] a,    
    input [15:0] b,    
    input sel,         
    output [15:0] out  
);
    // O multiplexador de 16 bits seleciona entre 'a' e 'b' (vetores de 16 bits) baseado em 'sel'.
    // Se sel=0, a saída 'out' é igual à entrada 'a'.
    // Se sel=1, a saída 'out' é igual à entrada 'b'.
    assign out = (sel == 1'b0) ? a : b;
endmodule

projeto1_portas_logicas/mux16/tb_mux16.v
`timescale 1ns / 1ps // define a unidade de tempo 

module tb_mux16;
    // declaração de sinais para conectar ao módulo DUT (Device Under Test)
    reg [15:0] input_a;    // entrada 'a' de 16 bits
    reg [15:0] input_b;    // entrada 'b' de 16 bits
    reg input_sel;         // entrada de seleção (1 bit)
    wire [15:0] output_out; // saída de 16 bits

    // instanciação do seu módulo mux16
    mux16 dut (
        .a(input_a),
        .b(input_b),
        .sel(input_sel),
        .out(output_out)
    );

    // bloco inicial: geração de estímulos, monitoramento e controle da simulação
    initial begin
        // configura o arquivo VCD para o GTKWave
        $dumpfile("mux16.vcd"); // o nome do arquivo de saída para as formas de onda
        $dumpvars(0, tb_mux16); // inclui todos os sinais no escopo atual (tb_mux16) para o .vcd

        // exibe o cabeçalho no console da simulação
        $display("Time | In_A (hex) | In_B (hex) | SEL | Out (hex)");
        // monitora e exibe as mudanças dos sinais no console
        $monitor("%0t | %h | %h | %b | %h", $time, input_a, input_b, input_sel, output_out);

        // --- cenários de teste para o Multiplexador de 16 bits ---

        // Inicializa todas as entradas
        input_a = 16'h0000; input_b = 16'hFFFF; input_sel = 0;
        #0.1;

        // Testes com SEL = 0
        input_sel = 0;
        input_a = 16'h1234; input_b = 16'hABCD; #5;
        input_a = 16'h5678; input_b = 16'hEFFE; #5; 
        input_a = 16'hFFFF; input_b = 16'h0000; #5;
        input_a = 16'h0000; input_b = 16'hFFFF; #5;

        #10; // Atraso maior para demarcar a mudança de SEL

        // Testes com SEL = 1
        input_sel = 1;
        input_a = 16'h1234; input_b = 16'hABCD; #5;
        input_a = 16'h5678; input_b = 16'hEFFE; #5; 
        input_a = 16'hFFFF; input_b = 16'h0000; #5;
        input_a = 16'h0000; input_b = 16'hFFFF; #5;
        
        $finish; 
    end

endmodule

projeto1_portas_logicas/mux16/mux16.vcd
$date
	Sat Jul  5 13:43:26 2025
$end
$version
	Icarus Verilog
$end
$timescale
	1ps
$end
$scope module tb_mux16 $end
$var wire 16 ! output_out [15:0] $end
$var reg 16 " input_a [15:0] $end
$var reg 16 # input_b [15:0] $end
$var reg 1 $ input_sel $end
$scope module dut $end
$var wire 16 % a [15:0] $end
$var wire 16 & b [15:0] $end
$var wire 1 $ sel $end
$var wire 16 ' out [15:0] $end
$upscope $end
$upscope $end
$enddefinitions $end
$comment Show the parameter values. $end
$dumpall
$end
#0
$dumpvars
b0 '
b1111111111111111 &
b0 %
0$
b1111111111111111 #
b0 "
b0 !
$end
#100
b1001000110100 !
b1001000110100 '
b1010101111001101 #
b1010101111001101 &
b1001000110100 "
b1001000110100 %
#5100
b101011001111000 !
b101011001111000 '
b1110111111111110 #
b1110111111111110 &
b101011001111000 "
b101011001111000 %
#10100
b1111111111111111 !
b1111111111111111 '
b0 #
b0 &
b1111111111111111 "
b1111111111111111 %
#15100
b0 !
b0 '
b1111111111111111 #
b1111111111111111 &
b0 "
b0 %
#30100
b1010101111001101 !
b1010101111001101 '
b1010101111001101 #
b1010101111001101 &
b1001000110100 "
b1001000110100 %
1$
#35100
b1110111111111110 !
b1110111111111110 '
b1110111111111110 #
b1110111111111110 &
b101011001111000 "
b101011001111000 %
#40100
b0 !
b0 '
b0 #
b0 &
b1111111111111111 "
b1111111111111111 %
#45100
b1111111111111111 !
b1111111111111111 '
b1111111111111111 #
b1111111111111111 &
b0 "
b0 %
