projeto1_portas_logicas/mux4way16/mux4way16.v
module mux4way16(
    input [15:0] a,    // Primeira entrada de 16 bits
    input [15:0] b,    // Segunda entrada de 16 bits
    input [15:0] c,    // Terceira entrada de 16 bits
    input [15:0] d,    // Quarta entrada de 16 bits
    input [1:0] sel,   // Sinal de seleção de 2 bits
    output [15:0] out  // Saída de 16 bits
);
    // Declaração de um reg temporário para a saída dentro do bloco always
    reg [15:0] temp_out;

    // Implementa o multiplexador de 4 para 1
    // Usa uma instrução case para selecionar a saída baseada em 'sel'
    always @(*) begin
        case (sel)
            2'b00: temp_out = a;
            2'b01: temp_out = b;
            2'b10: temp_out = c;
            2'b11: temp_out = d;
            default: temp_out = 16'bx; // Saída indefinida para seleções inválidas
        endcase
    end
    
    assign out = temp_out; // Atribui o valor do reg 'temp_out' para a saída 'out' (que é um wire)
endmodule

projeto1_portas_logicas/mux4way16/tb_mux4way16.v
`timescale 1ns / 1ps // define a unidade de tempo (1ns) e a precisão (1ps) da simulação

module tb_mux4way16;
    // declaração de sinais para conectar ao módulo DUT (Device Under Test)
    reg [15:0] input_a;    // entrada 'a' de 16 bits
    reg [15:0] input_b;    // entrada 'b' de 16 bits
    reg [15:0] input_c;    // entrada 'c' de 16 bits
    reg [15:0] input_d;    // entrada 'd' de 16 bits
    reg [1:0] input_sel;   // entrada de seleção de 2 bits
    wire [15:0] output_out; // saída de 16 bits

    // instanciação do seu módulo mux4way16
    mux4way16 dut (
        .a(input_a),
        .b(input_b),
        .c(input_c),
        .d(input_d),
        .sel(input_sel),
        .out(output_out)
    );

    // bloco inicial: geração de estímulos, monitoramento e controle da simulação
    initial begin
        // configura o arquivo VCD para o GTKWave
        $dumpfile("mux4way16.vcd"); // o nome do arquivo de saída para as formas de onda
        $dumpvars(0, tb_mux4way16); // inclui todos os sinais no escopo atual (tb_mux4way16) para o .vcd

        // exibe o cabeçalho no console da simulação
        $display("Time | In_A (hex) | In_B (hex) | In_C (hex) | In_D (hex) | SEL (bin) | Out (hex)");
        // monitora e exibe as mudanças dos sinais no console
        $monitor("%0t | %h | %h | %h | %h | %b | %h", $time, input_a, input_b, input_c, input_d, input_sel, output_out);

        // Inicializa todas as entradas
        input_a = 16'hAAAA; input_b = 16'hBBBB; input_c = 16'hCCCC; input_d = 16'hDDDD; input_sel = 2'b00;
        #0.1;

        // Testes com SEL = 00 (Saída deve ser igual a Input_A)
        input_sel = 2'b00;
        input_a = 16'h1111; input_b = 16'h2222; input_c = 16'h3333; input_d = 16'h4444; #5;
        input_a = 16'hAAAA; input_b = 16'hBBBB; input_c = 16'hCCCC; input_d = 16'hDDDD; #5;
        #10;

        // Testes com SEL = 01 (Saída deve ser igual a Input_B)
        input_sel = 2'b01;
        input_a = 16'h1111; input_b = 16'h2222; input_c = 16'h3333; input_d = 16'h4444; #5;
        input_a = 16'hAAAA; input_b = 16'hBBBB; input_c = 16'hCCCC; input_d = 16'hDDDD; #5;
        #10;

        // Testes com SEL = 10 (Saída deve ser igual a Input_C)
        input_sel = 2'b10;
        input_a = 16'h1111; input_b = 16'h2222; input_c = 16'h3333; input_d = 16'h4444; #5;
        input_a = 16'hAAAA; input_b = 16'hBBBB; input_c = 16'hCCCC; input_d = 16'hDDDD; #5;
        #10;

        // Testes com SEL = 11 (Saída deve ser igual a Input_D)
        input_sel = 2'b11;
        input_a = 16'h1111; input_b = 16'h2222; input_c = 16'h3333; input_d = 16'h4444; #5;
        input_a = 16'hAAAA; input_b = 16'hBBBB; input_c = 16'hCCCC; input_d = 16'hDDDD; #5;
        #10;
        
        $finish; // termina a simulação
    end

endmodule

projeto1_portas_logicas/mux4way16/mux4way16.vcd
$date
	Sat Jul  5 13:53:34 2025
$end
$version
	Icarus Verilog
$end
$timescale
	1ps
$end
$scope module tb_mux4way16 $end
$var wire 16 ! output_out [15:0] $end
$var reg 16 " input_a [15:0] $end
$var reg 16 # input_b [15:0] $end
$var reg 16 $ input_c [15:0] $end
$var reg 16 % input_d [15:0] $end
$var reg 2 & input_sel [1:0] $end
$scope module dut $end
$var wire 16 ' a [15:0] $end
$var wire 16 ( b [15:0] $end
$var wire 16 ) c [15:0] $end
$var wire 16 * d [15:0] $end
$var wire 16 + out [15:0] $end
$var wire 2 , sel [1:0] $end
$var reg 16 - temp_out [15:0] $end
$upscope $end
$upscope $end
$enddefinitions $end
$comment Show the parameter values. $end
$dumpall
$end
#0
$dumpvars
b1010101010101010 -
b0 ,
b1010101010101010 +
b1101110111011101 *
b1100110011001100 )
b1011101110111011 (
b1010101010101010 '
b0 &
b1101110111011101 %
b1100110011001100 $
b1011101110111011 #
b1010101010101010 "
b1010101010101010 !
$end
#100
b1000100010001 !
b1000100010001 +
b1000100010001 -
b100010001000100 %
b100010001000100 *
b11001100110011 $
b11001100110011 )
b10001000100010 #
b10001000100010 (
b1000100010001 "
b1000100010001 '
#5100
b1010101010101010 !
b1010101010101010 +
b1010101010101010 -
b1101110111011101 %
b1101110111011101 *
b1100110011001100 $
b1100110011001100 )
b1011101110111011 #
b1011101110111011 (
b1010101010101010 "
b1010101010101010 '
#20100
b10001000100010 !
b10001000100010 +
b10001000100010 -
b100010001000100 %
b100010001000100 *
b11001100110011 $
b11001100110011 )
b10001000100010 #
b10001000100010 (
b1000100010001 "
b1000100010001 '
b1 &
b1 ,
#25100
b1011101110111011 !
b1011101110111011 +
b1011101110111011 -
b1101110111011101 %
b1101110111011101 *
b1100110011001100 $
b1100110011001100 )
b1011101110111011 #
b1011101110111011 (
b1010101010101010 "
b1010101010101010 '
#40100
b11001100110011 !
b11001100110011 +
b11001100110011 -
b100010001000100 %
b100010001000100 *
b11001100110011 $
b11001100110011 )
b10001000100010 #
b10001000100010 (
b1000100010001 "
b1000100010001 '
b10 &
b10 ,
#45100
b1100110011001100 !
b1100110011001100 +
b1100110011001100 -
b1101110111011101 %
b1101110111011101 *
b1100110011001100 $
b1100110011001100 )
b1011101110111011 #
b1011101110111011 (
b1010101010101010 "
b1010101010101010 '
#60100
b100010001000100 !
b100010001000100 +
b100010001000100 -
b100010001000100 %
b100010001000100 *
b11001100110011 $
b11001100110011 )
b10001000100010 #
b10001000100010 (
b1000100010001 "
b1000100010001 '
b11 &
b11 ,
#65100
b1101110111011101 !
b1101110111011101 +
b1101110111011101 -
b1101110111011101 %
b1101110111011101 *
b1100110011001100 $
b1100110011001100 )
b1011101110111011 #
b1011101110111011 (
b1010101010101010 "
b1010101010101010 '
