project3/ram16k/ram16k.v
module ram16k (
    input [15:0] in,
    input [13:0] address,
    input load,
    input clk,
    output reg [15:0] out
);

    reg [15:0] ram [16383:0];
    integer i;

    initial begin
        for (i = 0; i < 16384; i = i + 1)
            ram[i] = 16'h0000;
    end

    always @(posedge clk) begin
        if (load)
            ram[address] <= in;
        out <= ram[address];
    end

endmodule

project3/ram16k/tb_ram16k.v
module tb_ram16k;

reg clk;
reg load;
reg [13:0] address;
reg [15:0] in;
wire [15:0] out;

ram16k uut (
    .clk(clk),
    .load(load),
    .address(address),
    .in(in),
    .out(out)
);

initial clk = 0;
always #5 clk = ~clk;

initial begin
    $dumpfile("ram16k.vcd");
    $dumpvars(0, tb_ram16k);

    load = 0; address = 14'b00000000000000; in = 16'h0000;
    #10;

    load = 1; address = 14'b00000000000010; in = 16'habcd;  // escreve na posição 2
    #10;
    load = 0;
    #10;

    address = 14'b00000000000010; // lê da posição 2
    #10;

    load = 1; address = 14'b11111111111111; in = 16'h1234;  // escreve na posição 16383
    #10;
    load = 0;
    #10;

    address = 14'b11111111111111; // lê da posição 16383
    #10;

    address = 14'b00000000000000; // lê da posição 0 (sem escrita)
    #10;

    $finish;
end

endmodule

project3/ram16k/ram16k.vcd
$date
	Thu Jul 24 16:43:08 2025
$end
$version
	Icarus Verilog
$end
$timescale
	1s
$end
$scope module tb_ram16k $end
$var wire 16 ! out [15:0] $end
$var reg 14 " address [13:0] $end
$var reg 1 # clk $end
$var reg 16 $ in [15:0] $end
$var reg 1 % load $end
$scope module uut $end
$var wire 14 & address [13:0] $end
$var wire 1 # clk $end
$var wire 16 ' in [15:0] $end
$var wire 1 % load $end
$var reg 16 ( out [15:0] $end
$var integer 32 ) i [31:0] $end
$upscope $end
$upscope $end
$enddefinitions $end
$comment Show the parameter values. $end
$dumpall
$end
#0
$dumpvars
b100000000000000 )
bx (
b0 '
b0 &
0%
b0 $
0#
b0 "
bx !
$end
#5
b0 !
b0 (
1#
#10
0#
b1010101111001101 $
b1010101111001101 '
b10 "
b10 &
1%
#15
1#
#20
0#
0%
#25
b1010101111001101 !
b1010101111001101 (
1#
#30
0#
#35
1#
#40
0#
b1001000110100 $
b1001000110100 '
b11111111111111 "
b11111111111111 &
1%
#45
b0 !
b0 (
1#
#50
0#
0%
#55
b1001000110100 !
b1001000110100 (
1#
#60
0#
#65
1#
#70
0#
b0 "
b0 &
#75
b0 !
b0 (
1#
