projeto5_cpu/alu.v
module alu(
    // entradas
    input [15:0] x, 
    input [15:0] y,     
    input zx, 
    input nx, 
    input zy, 
    input ny, 
    input f, 
    input no,
    // saidas
    output reg [15:0] out,      
    output zr, 
    output ng    
);

    // combina os sinais de controle em um unico barramento
    wire [5:0] sel;
    assign sel = {zx, nx, zy, ny, f, no};

    // operacao da alu seguindo os sinais de controle
    always @(*) begin
        case (sel)
            6'b101010: out = 0;         // zero
            6'b111111: out = 1;         // um
            6'b111010: out = -1;        // menos um
            6'b001100: out = x;         // passa x
            6'b110000: out = y;         // passa y
            6'b001101: out = ~x;        // not x
            6'b110001: out = ~y;        // not y
            6'b001111: out = -x;        // negativo de x
            6'b110011: out = -y;        // negativo de y
            6'b011111: out = x + 1;     // incrementa x
            6'b110111: out = y + 1;     // incrementa y
            6'b000010: out = x + y;     // soma x e y
            6'b010011: out = x - y;     // subtrai y de x
            6'b000111: out = y - x;     // subtrai x de y
            6'b000000: out = x & y;     // and x e y
            6'b010101: out = x | y;     // or x e y
            default: out = 16'hxxxx;    // operacao indefinida
        endcase
    end

    // sinal de zero-> ativado se a saida for zero
    assign zr = (out == 0) ? 1 : 0;

    // sinal de negativo-> ativado se o bit mais significativo da saida for 1
    assign ng = out[15];

endmodule

projeto5_cpu/cpu.v
`include "alu.v"
module CPU(
    input wire clk,
    input wire [15:0] inM,          // entrada do valor M (M = conteudo da RAM[A])
    input wire [15:0] instruction,  // instrucao para execucao
    input wire reset,               // indica se deve reiniciar o programa atual
                                    // (reset==1) ou continuar executando o
                                    // programa atual (reset==0).

    output wire [15:0] outM,        // saida do valor M
    output wire loadM,              // escrever em M?
    output wire [15:0] addressM,    // endereco na memoria de dados (de M) para leitura
    output reg [15:0] pc            // endereco da proxima instrucao
);

    assign addressM = regA;
    wire loadI;
    wire loadA;
    wire loadD;
    assign outM = outALU;    
    wire [15:0] am;
    assign am = (instruction[12]) ? inM : regA;
    wire lt;
    wire eq;
    wire jmp;
    wire inc;
    wire [15:0] outALU;
        
    reg [15:0] regA;
    reg [15:0] regD;


    // sinais de controle para carregamento de registradores
    assign loadI = ~instruction[15]; // carrega instrucao no registrador A se o bit 15 for 0
    assign loadA = instruction[15] & instruction[5]; // carrega valor no registrador A se o bit 15 e o bit 5 forem 1
    assign loadD = instruction[15] & instruction[4]; // carrega valor no registrador D se o bit 15 e o bit 4 forem 1
    assign loadM = instruction[15] & instruction[3]; // carrega valor na memoria se o bit 15 e o bit 3 forem 1

    // logica de salto condicional
    assign jmp = instruction[15] & ((lt & instruction[2]) | (eq & instruction[1]) | ((!(lt | eq)) & instruction[0]));

    // logica de atualizacao do contador de programa (pc)
    always @(posedge clk) begin
        if (reset) 
            pc <= 0; // reseta o PC para 0
        else if (jmp) 
            pc <= regA; // salta para o endereco no registrador A
        else 
            pc <= pc + 1; // incrementa o PC
    end

    // logica de atualizacao do registrador A
    always @(posedge clk) begin
        if (reset) 
            regA <= 0; // reseta o registrador A para 0
        else if (loadI) 
            regA <= instruction; // carrega a instrucao no registrador A
        else if (loadA) 
            regA <= outALU; // carrega o valor da ALU no registrador A
        else 
            regA <= regA; // mantem o valor atual do registrador A
    end

    // logica de atualizacao do registrador D
    always @(posedge clk) begin
        if (reset) 
            regD <= 0; // reseta o registrador D para 0
        else if (loadD) 
            regD <= outALU; // carrega o valor da ALU no registrador D
        else 
            regD <= regD; // mantem o valor atual do registrador D
    end

endmodule

projeto5_cpu/tb_cpu.v
`include "CPU.v"

module tb_CPU;
    // definicoes dos sinais
    reg clk;                     // clock
    reg reset;                   // sinal de reset
    reg [15:0] inM;              // valor de entrada M (memoria)
    reg [15:0] instruction;      // instrucao para execucao
    wire [15:0] outM;            // valor de saida M (memoria)
    wire loadM;                  // sinal para escrever em M
    wire [15:0] addressM;        // endereco da memoria de dados (M)
    wire [15:0] pc;              // contador de programa (program counter)

    // instancia da CPU
    CPU uut (
        .clk(clk),
        .inM(inM),
        .instruction(instruction),
        .reset(reset),
        .outM(outM),
        .loadM(loadM),
        .addressM(addressM),
        .pc(pc)
    );

    // gerador de clock
    always
        #1 clk = ~clk;  

    // como os sinais irao variar durante a simulacao
    initial begin
        $display("testando o modulo CPU");
        $dumpfile("signals.vcd");
        $dumpvars(0, tb_CPU);
        // inicializando os sinais
        clk = 0;
        reset = 0;
        inM = 16'd0;
        instruction = 16'd0;

        // resetando a CPU
        reset = 1;
        #2;
        reset = 0;

        // teste 1: carregar @12345 no registrador A (A = 12345)
        instruction = 16'b0011000000111001;  // @12345
        #2;  // espera 2 unidades de tempo (um ciclo de clock completo)
        
        // teste 2: executar D=A (D = 12345)
        instruction = 16'b1110110000010000;  // D=A
        #2;

        // teste 3: carregar @23456 no registrador A (A = 23456)
        instruction = 16'b0101101110100000;  // @23456
        #2;

        // teste 4: executar D=A-D (D = A-D)
        instruction = 16'b1110000111010000;  // D=A-D
        #2;

        // teste 5: carregar @1000 no registrador A (A = 1000)
        instruction = 16'b0000001111101000;  // @1000
        #2;

        // teste 6: executar M=D (M = D)
        instruction = 16'b1110001100001000;  // M=D
        #2;

        // teste 7: carregar @1001 no registrador A (A = 1001)
        instruction = 16'b0000001111101001;  // @1001
        #2;

        // teste 8: executar MD=D-1 (M e D = D-1)
        instruction = 16'b1110001110011000;  // MD=D-1
        #2;

        // teste 9: carregar @1000 no registrador A (A = 1000)
        instruction = 16'b0000001111101000;  // @1000
        #2;

        // teste 10: executar D=D-M (D = D - M)
        instruction = 16'b1111010011010000;  // D=D-M
        inM = 16'b11111;                     // define inM como 11111 (valor da memoria)
        #2;

        // continue com os outros testes conforme necessario, usando o mesmo padrao de delays e configuracoes.
        
        // finalizando a simulacao
        $finish;
    end

endmodule

projeto5_cpu/signals.vcd
$date
	Mon Aug 25 13:54:13 2025
$end
$version
	Icarus Verilog
$end
$timescale
	1s
$end
$scope module tb_CPU $end
$var wire 16 ! pc [15:0] $end
$var wire 16 " outM [15:0] $end
$var wire 1 # loadM $end
$var wire 16 $ addressM [15:0] $end
$var reg 1 % clk $end
$var reg 16 & inM [15:0] $end
$var reg 16 ' instruction [15:0] $end
$var reg 1 ( reset $end
$scope module uut $end
$var wire 16 ) addressM [15:0] $end
$var wire 1 % clk $end
$var wire 1 * eq $end
$var wire 16 + inM [15:0] $end
$var wire 16 , instruction [15:0] $end
$var wire 1 - jmp $end
$var wire 1 . loadA $end
$var wire 1 / loadD $end
$var wire 1 0 loadI $end
$var wire 1 # loadM $end
$var wire 1 1 lt $end
$var wire 16 2 outALU [15:0] $end
$var wire 16 3 outM [15:0] $end
$var wire 1 ( reset $end
$var wire 16 4 am [15:0] $end
$var reg 16 5 pc [15:0] $end
$var reg 16 6 regA [15:0] $end
$var reg 16 7 regD [15:0] $end
$upscope $end
$upscope $end
$enddefinitions $end
$comment Show the parameter values. $end
$dumpall
$end
#0
$dumpvars
bx 7
bx 6
bx 5
bx 4
bz 3
bz 2
z1
10
0/
0.
0-
b0 ,
b0 +
z*
bx )
1(
b0 '
b0 &
0%
bx $
0#
bz "
bx !
$end
#1
b0 4
b0 !
b0 5
b0 $
b0 )
b0 6
b0 7
1%
#2
0%
b11000000111001 '
b11000000111001 ,
0(
#3
b11000000111001 $
b11000000111001 )
b11000000111001 6
b1 !
b1 5
1%
#4
b11000000111001 4
00
1/
0-
0%
b1110110000010000 '
b1110110000010000 ,
#5
b10 !
b10 5
bz 7
1%
#6
b0 4
10
0/
0%
b101101110100000 '
b101101110100000 ,
#7
b101101110100000 $
b101101110100000 )
b101101110100000 6
b11 !
b11 5
1%
#8
b101101110100000 4
00
1/
0%
b1110000111010000 '
b1110000111010000 ,
#9
b100 !
b100 5
1%
#10
10
0/
0%
b1111101000 '
b1111101000 ,
#11
b1111101000 4
b1111101000 $
b1111101000 )
b1111101000 6
b101 !
b101 5
1%
#12
00
1#
0%
b1110001100001000 '
b1110001100001000 ,
#13
b110 !
b110 5
1%
#14
10
0#
0%
b1111101001 '
b1111101001 ,
#15
b1111101001 4
b1111101001 $
b1111101001 )
b1111101001 6
b111 !
b111 5
1%
#16
00
1/
1#
0-
0%
b1110001110011000 '
b1110001110011000 ,
#17
b1000 !
b1000 5
1%
#18
10
0/
0#
0%
b1111101000 '
b1111101000 ,
#19
b1111101000 4
b1111101000 $
b1111101000 )
b1111101000 6
b1001 !
b1001 5
1%
#20
b11111 4
00
1/
0%
b11111 &
b11111 +
b1111010011010000 '
b1111010011010000 ,
#21
b1010 !
b1010 5
1%
