project3/bit/tb_bit.v
module tb_bit;

reg clk;
reg load;
reg in;
wire out;

bit bit_inst (
    .clk(clk),
    .load(load),
    .in(in),
    .out(out)
);

initial clk = 0;
always #5 clk = ~clk;

initial begin
    $dumpfile("bit.vcd");
    $dumpvars(0, tb_bit);

    load = 0; in = 0;
    #10;

    load = 1; in = 1; // carregar 1
    #10;
    load = 0; in = 0;
    #10;

    load = 1; in = 0; // carregar 0
    #10;
    load = 0;
    #10;

    load = 1; in = 1; // carregar 1 de novo
    #10;

    $finish;
end

endmodule

project3/bit/bit.vcd
$date
	Thu Jul 24 17:15:23 2025
$end
$version
	Icarus Verilog
$end
$timescale
	1s
$end
$scope module tb_bit $end
$var wire 1 ! out $end
$var reg 1 " clk $end
$var reg 1 # in $end
$var reg 1 $ load $end
$scope module bit_inst $end
$var wire 1 " clk $end
$var wire 1 # in $end
$var wire 1 $ load $end
$var reg 1 ! out $end
$upscope $end
$upscope $end
$enddefinitions $end
$comment Show the parameter values. $end
$dumpall
$end
#0
$dumpvars
0$
0#
0"
0!
$end
#5
1"
#10
0"
1#
1$
#15
1!
1"
#20
0"
0#
0$
#25
1"
#30
0"
1$
#35
0!
1"
#40
0"
0$
#45
1"
#50
0"
1#
1$
#55
1!
1"
