project3/ram4k/ram4k.v
module ram4k (
    input [15:0] in,
    input [11:0] address,
    input load,
    input clk,
    output reg [15:0] out
);

    reg [15:0] ram [4095:0];
    integer i;

    initial begin
        for (i = 0; i < 4096; i = i + 1)
            ram[i] = 16'h0000;
    end

    always @(posedge clk) begin
        if (load)
            ram[address] <= in;
        out <= ram[address];
    end

endmodule

project3/ram4k/tb_ram4k.v
module tb_ram4k;

reg clk;
reg load;
reg [11:0] address;
reg [15:0] in;
wire [15:0] out;

ram4k uut (
    .clk(clk),
    .load(load),
    .address(address),
    .in(in),
    .out(out)
);

initial clk = 0;
always #5 clk = ~clk;

initial begin
    $dumpfile("ram4k.vcd");
    $dumpvars(0, tb_ram4k);

    load = 0; address = 12'b000000000000; in = 16'h0000;
    #10;

    load = 1; address = 12'b000000000010; in = 16'habcd;  // escreve na posição 2
    #10;
    load = 0;
    #10;

    address = 12'b000000000010; // lê da posição 2
    #10;

    load = 1; address = 12'b111111111111; in = 16'h1234;  // escreve na posição 4095
    #10;
    load = 0;
    #10;

    address = 12'b111111111111; // lê da posição 4095
    #10;

    address = 12'b000000000000; // lê da posição 0 (sem escrita)
    #10;

    $finish;
end

endmodule

project3/ram4k/ram4k.vcd
$date
	Thu Jul 24 16:40:51 2025
$end
$version
	Icarus Verilog
$end
$timescale
	1s
$end
$scope module tb_ram4k $end
$var wire 16 ! out [15:0] $end
$var reg 12 " address [11:0] $end
$var reg 1 # clk $end
$var reg 16 $ in [15:0] $end
$var reg 1 % load $end
$scope module uut $end
$var wire 12 & address [11:0] $end
$var wire 1 # clk $end
$var wire 16 ' in [15:0] $end
$var wire 1 % load $end
$var reg 16 ( out [15:0] $end
$var integer 32 ) i [31:0] $end
$upscope $end
$upscope $end
$enddefinitions $end
$comment Show the parameter values. $end
$dumpall
$end
#0
$dumpvars
b1000000000000 )
bx (
b0 '
b0 &
0%
b0 $
0#
b0 "
bx !
$end
#5
b0 !
b0 (
1#
#10
0#
b1010101111001101 $
b1010101111001101 '
b10 "
b10 &
1%
#15
1#
#20
0#
0%
#25
b1010101111001101 !
b1010101111001101 (
1#
#30
0#
#35
1#
#40
0#
b1001000110100 $
b1001000110100 '
b111111111111 "
b111111111111 &
1%
#45
b0 !
b0 (
1#
#50
0#
0%
#55
b1001000110100 !
b1001000110100 (
1#
#60
0#
#65
1#
#70
0#
b0 "
b0 &
#75
b0 !
b0 (
1#
