hack-arithmetic-project/fulladder/fulladder.v
module fulladder (
    input wire a,
    input wire b,
    input wire cin,
    output wire sum,
    output wire cout
);
    assign sum = a ^ b ^ cin;
    assign cout = (a & b) | (a & cin) | (b & cin);
endmodule

hack-arithmetic-project/fulladder/tb_fulladder.v
`timescale 1ns / 1ps

module tb_fulladder;

    reg a, b, cin;
    wire sum, cout;

    fulladder uut (
        .a(a),
        .b(b),
        .cin(cin),
        .sum(sum),
        .cout(cout)
    );

    initial begin
        $dumpfile("fulladder.vcd");
        $dumpvars(0, tb_fulladder);
        $display("A B Cin | Sum Cout");
        $monitor("%b %b  %b  |  %b    %b", a, b, cin, sum, cout);

        a = 0; b = 0; cin = 0; #10;
        a = 0; b = 0; cin = 1; #10;
        a = 0; b = 1; cin = 0; #10;
        a = 0; b = 1; cin = 1; #10;
        a = 1; b = 0; cin = 0; #10;
        a = 1; b = 0; cin = 1; #10;
        a = 1; b = 1; cin = 0; #10;
        a = 1; b = 1; cin = 1; #10;

        $finish;
    end

endmodule

hack-arithmetic-project/fulladder/fulladder.vcd
$date
	Fri Jul 11 13:27:35 2025
$end
$version
	Icarus Verilog
$end
$timescale
	1ps
$end
$scope module tb_fulladder $end
$var wire 1 ! sum $end
$var wire 1 " cout $end
$var reg 1 # a $end
$var reg 1 $ b $end
$var reg 1 % cin $end
$scope module uut $end
$var wire 1 # a $end
$var wire 1 $ b $end
$var wire 1 % cin $end
$var wire 1 " cout $end
$var wire 1 ! sum $end
$upscope $end
$upscope $end
$enddefinitions $end
$comment Show the parameter values. $end
$dumpall
$end
#0
$dumpvars
0%
0$
0#
0"
0!
$end
#10000
1!
1%
#20000
0%
1$
#30000
1"
0!
1%
#40000
0"
1!
0%
0$
1#
#50000
1"
0!
1%
#60000
0%
1$
#70000
1!
1%
