projeto1_portas_logicas/dmux4way/dmux4way.v
module dmux4way(
    input in,
    input [1:0] sel,
    output a,
    output b,
    output c,
    output d
);
    // Demultiplexador de 1 para 4
    // A entrada 'in' é direcionada para uma das 4 saídas (a, b, c, d)
    // conforme o valor de 'sel'. As outras saídas são 0.
    
    assign a = (sel == 2'b00) ? in : 1'b0;
    assign b = (sel == 2'b01) ? in : 1'b0;
    assign c = (sel == 2'b10) ? in : 1'b0;
    assign d = (sel == 2'b11) ? in : 1'b0;

endmodule

projeto1_portas_logicas/dmux4way/tb_dmux4way.v
`timescale 1ns / 1ps // define a unidade de tempo 

module tb_dmux4way;
    reg input_in;
    reg [1:0] input_sel;
    wire output_a;
    wire output_b;
    wire output_c;
    wire output_d;

    dmux4way dut (
        .in(input_in),
        .sel(input_sel),
        .a(output_a),
        .b(output_b),
        .c(output_c),
        .d(output_d)
    );

    initial begin
        $dumpfile("dmux4way.vcd");
        $dumpvars(0, tb_dmux4way);

        $display("Time | IN | SEL (bin) | OUT_A | OUT_B | OUT_C | OUT_D");
        $monitor("%0t | %b | %b | %b | %b | %b | %b", $time, input_in, input_sel, output_a, output_b, output_c, output_d);

        // --- cenários de teste para o Demultiplexador de 1 para 4 ---

        // Inicializa todas as entradas
        input_in = 0; input_sel = 2'b00;
        #0.1; // Pequeno atraso inicial

        // Testes com Input_IN = 1
        input_in = 1;

        input_sel = 2'b00; #5;
        input_sel = 2'b01; #5;
        input_sel = 2'b10; #5;
        input_sel = 2'b11; #5;

        // Testes com Input_IN = 0
        #10;

        input_in = 0;
        input_sel = 2'b00; #5;
        input_sel = 2'b01; #5;
        input_sel = 2'b10; #5;
        input_sel = 2'b11; #5;
        
        $finish;
    end

endmodule

projeto1_portas_logicas/dmux4way/dmux4way.vcd
$date
	Sat Jul  5 14:14:42 2025
$end
$version
	Icarus Verilog
$end
$timescale
	1ps
$end
$scope module tb_dmux4way $end
$var wire 1 ! output_d $end
$var wire 1 " output_c $end
$var wire 1 # output_b $end
$var wire 1 $ output_a $end
$var reg 1 % input_in $end
$var reg 2 & input_sel [1:0] $end
$scope module dut $end
$var wire 1 % in $end
$var wire 2 ' sel [1:0] $end
$var wire 1 ! d $end
$var wire 1 " c $end
$var wire 1 # b $end
$var wire 1 $ a $end
$upscope $end
$upscope $end
$enddefinitions $end
$comment Show the parameter values. $end
$dumpall
$end
#0
$dumpvars
b0 '
b0 &
0%
0$
0#
0"
0!
$end
#100
1$
1%
#5100
0$
1#
b1 &
b1 '
#10100
0#
1"
b10 &
b10 '
#15100
0"
1!
b11 &
b11 '
#30100
0!
b0 &
b0 '
0%
#35100
b1 &
b1 '
#40100
b10 &
b10 '
#45100
b11 &
b11 '
