projeto1_portas_logicas/mux/mux.v
module mux(
    input a,
    input b,
    input sel, 
    output out
);
    //  multiplexador seleciona entre 'a' e 'b' baseado em 'sel'
    // Se sel=0, out=a. Se sel=1, out=b.
    assign out = (sel == 0) ? a : b; 
endmodule

projeto1_portas_logicas/mux/tb_mux.v
`timescale 1ns / 1ps // define a unidade de tempo 

module tb_mux;
    // declaração de sinais para conectar ao módulo DUT (Device Under Test)
    reg input_a;    // entrada 'a' do multiplexador
    reg input_b;    // entrada 'b' do multiplexador
    reg input_sel;  // entrada de seleção 'sel'
    wire output_out; // saída do multiplexador

    // instanciação do seu módulo mux
    mux dut (
        .a(input_a),
        .b(input_b),
        .sel(input_sel),
        .out(output_out)
    );

    // bloco inicial: geração de estímulos, monitoramento e controle da simulação
    initial begin
        // configura o arquivo VCD para o GTKWave
        $dumpfile("mux.vcd"); // o nome do arquivo de saída para as formas de onda
        $dumpvars(0, tb_mux); // inclui todos os sinais no escopo atual (tb_mux) para o .vcd

        // exibe o cabeçalho no console da simulação
        $display("Time | Input_A | Input_B | Input_SEL | Output_Out");
        // monitora e exibe as mudanças dos sinais no console
        $monitor("%0t | %b | %b | %b | %b", $time, input_a, input_b, input_sel, output_out);

        // --- cenários de teste para o Multiplexador (Tabela Verdade) ---
        // SEL | A | B | OUT
        // 0   | 0 | 0 | 0 (saída = A)
        // 0   | 0 | 1 | 0 (saída = A)
        // 0   | 1 | 0 | 1 (saída = A)
        // 0   | 1 | 1 | 1 (saída = A)
        // 1   | 0 | 0 | 0 (saída = B)
        // 1   | 0 | 1 | 1 (saída = B)
        // 1   | 1 | 0 | 0 (saída = B)
        // 1   | 1 | 1 | 1 (saída = B)

        // testes com SEL = 0 (deve passar A para a saída)
        input_sel = 0;
        input_a = 0; input_b = 0; #0.1; 
        input_a = 0; input_b = 1; #0.1; 
        input_a = 1; input_b = 0; #0.1; 
        input_a = 1; input_b = 1; #0.1; 

        // testes com SEL = 1 (deve passar B para a saída)
        input_sel = 1;
        input_a = 0; input_b = 0; #0.1; 
        input_a = 0; input_b = 1; #0.1; 
        input_a = 1; input_b = 0; #0.1; 
        input_a = 1; input_b = 1; #0.1; 

        $finish; 
    end

endmodule

projeto1_portas_logicas/mux/mux.vcd
$date
	Wed Jul  9 14:46:59 2025
$end
$version
	Icarus Verilog
$end
$timescale
	1ps
$end
$scope module tb_mux $end
$var wire 1 ! output_out $end
$var reg 1 " input_a $end
$var reg 1 # input_b $end
$var reg 1 $ input_sel $end
$scope module dut $end
$var wire 1 " a $end
$var wire 1 # b $end
$var wire 1 $ sel $end
$var wire 1 ! out $end
$upscope $end
$upscope $end
$enddefinitions $end
$comment Show the parameter values. $end
$dumpall
$end
#0
$dumpvars
0$
0#
0"
0!
$end
#100
1#
#200
1!
0#
1"
#300
1#
#400
0!
0#
0"
1$
#500
1!
1#
#600
0!
0#
1"
#700
1!
1#
